paud/__init__.py
paud/__main__.py
paud/audio.py
paud/check_system.py
paud/frame.py
paud/libdata.py
paud/play.py
paud-0.1.dist-info/entry_points.txt
paud-0.1.dist-info/LICENSE
paud-0.1.dist-info/WHEEL
paud-0.1.dist-info/METADATA
paud-0.1.dist-info/RECORD
