Metadata-Version: 2.1
Name: paud
Version: 0.1
Summary: Python library to process audio
Home-page: https://github.com/ASVIEST/paud
License: GPL-3.0-or-later
Author: ASVIEST
Author-email: 71895914+ASVIEST@users.noreply.github.com
Requires-Python: >=3.7,<4.0
Classifier: Development Status :: 2 - Pre-Alpha
Classifier: License :: OSI Approved :: GNU General Public License v3 or later (GPLv3+)
Classifier: Programming Language :: Python :: 3
Classifier: Programming Language :: Python :: 3.7
Classifier: Programming Language :: Python :: 3.8
Project-URL: Repository, https://github.com/ASVIEST/paud
